django_dburl.py
django_dburl-1.0.0.dist-info/LICENSE
django_dburl-1.0.0.dist-info/METADATA
django_dburl-1.0.0.dist-info/WHEEL
django_dburl-1.0.0.dist-info/top_level.txt
django_dburl-1.0.0.dist-info/RECORD
